Metadata-Version: 2.1
Name: RegexOrder
Version: 0.1
Summary: Search the regex that fits all querying strings.
Home-page: https://github.com/chuanconggao/RegexOrder
Author: Chuancong Gao
Author-email: chuancong@gmail.com
License: MIT
Download-URL: https://github.com/chuanconggao/RegexOrder/tarball/0.1
Keywords: regex,string-matchingpartial-order
Platform: UNKNOWN
Classifier: Operating System :: OS Independent
Classifier: Programming Language :: Python
Classifier: Programming Language :: Python :: 3
Requires-Python: >= 3
